fastutils_hmarcuzzo/__init__.py
fastutils_hmarcuzzo/applications.py
fastutils_hmarcuzzo/common/__init__.py
fastutils_hmarcuzzo/common/database/__init__.py
fastutils_hmarcuzzo/common/database/abstract_repository.py
fastutils_hmarcuzzo/common/database/redis/__init__.py
fastutils_hmarcuzzo/common/database/redis/client.py
fastutils_hmarcuzzo/common/database/sqlalchemy/__init__.py
fastutils_hmarcuzzo/common/database/sqlalchemy/async_base_repository.py
fastutils_hmarcuzzo/common/database/sqlalchemy/base.py
fastutils_hmarcuzzo/common/database/sqlalchemy/base_entity.py
fastutils_hmarcuzzo/common/database/sqlalchemy/repository_utils/__init__.py
fastutils_hmarcuzzo/common/database/sqlalchemy/repository_utils/base_repository_utils.py
fastutils_hmarcuzzo/common/database/sqlalchemy/repository_utils/inject_db_parameter_decorator.py
fastutils_hmarcuzzo/common/database/sqlalchemy/repository_utils/select_constructor.py
fastutils_hmarcuzzo/common/database/sqlalchemy/session.py
fastutils_hmarcuzzo/common/database/sqlalchemy/sync_base_repository.py
fastutils_hmarcuzzo/common/schema/__init__.py
fastutils_hmarcuzzo/common/schema/base_schema.py
fastutils_hmarcuzzo/common/schema/custom_base_model_schema.py
fastutils_hmarcuzzo/common/schema/exception_response_schema.py
fastutils_hmarcuzzo/constants/__init__.py
fastutils_hmarcuzzo/constants/regex_expressions.py
fastutils_hmarcuzzo/decorators/__init__.py
fastutils_hmarcuzzo/decorators/db_session_decorator.py
fastutils_hmarcuzzo/decorators/pagination_with_search_decorator.py
fastutils_hmarcuzzo/decorators/simple_pagination_decorator.py
fastutils_hmarcuzzo/handlers/__init__.py
fastutils_hmarcuzzo/handlers/http_exceptions_handler.py
fastutils_hmarcuzzo/middlewares/__init__.py
fastutils_hmarcuzzo/middlewares/db_session_middleware.py
fastutils_hmarcuzzo/types/__init__.py
fastutils_hmarcuzzo/types/custom_base_exception.py
fastutils_hmarcuzzo/types/custom_enum.py
fastutils_hmarcuzzo/types/custom_pages.py
fastutils_hmarcuzzo/types/delete_result.py
fastutils_hmarcuzzo-0.6.0.dist-info/LICENSE
fastutils_hmarcuzzo-0.6.0.dist-info/METADATA
fastutils_hmarcuzzo-0.6.0.dist-info/WHEEL
fastutils_hmarcuzzo-0.6.0.dist-info/RECORD
