Metadata-Version: 2.3
Name: fastutils-hmarcuzzo
Version: 0.6.0
Summary: A personal utility library I've developed to streamline and optimize backend development with FastAPI in my projects. From generic repositories and queries to enums, error handling, and more, fastutils_hmarcuzzo encompasses essential tools that have proven invaluable in my development journey, whether as a novice or a seasoned professional.
License: MIT
Author: Henrique Marcuzzo
Author-email: henrique.souza.m06@gmail.com
Requires-Python: >=3.10,<3.13
Classifier: License :: OSI Approved :: MIT License
Classifier: Programming Language :: Python :: 3
Classifier: Programming Language :: Python :: 3.10
Classifier: Programming Language :: Python :: 3.11
Classifier: Programming Language :: Python :: 3.12
Provides-Extra: redis
Requires-Dist: fastapi (>=0.115.10,<0.116.0)
Requires-Dist: fastapi-pagination (>=0.12.34,<0.13.0)
Requires-Dist: pydantic (>=2.10.6,<3.0.0)
Requires-Dist: redis (>=5.2.1,<6.0.0) ; extra == "redis"
Requires-Dist: sqlalchemy (>=2.0.38,<3.0.0)
Requires-Dist: sqlalchemy-utils (>=0.41.2,<0.42.0)
Requires-Dist: uuid6 (>=2024.7.10,<2025.0.0)
